[
    {
        "name": "",
        "face": "",
        "string": "伊拉修莱德",
        "special": "dia3"
    },
    {
        "name": "夏修伦",
        "face": "夏修伦",
        "string": "我们到了，伊拉修莱德",
        "special": "dia2"
    },
    {
        "name": "洛雨希",
        "face": "洛雨希",
        "string": "和传闻的一样，空气中有一种湿润的感觉",
        "special": "dia2"
    },
    {
        "name": "伊丽丝",
        "face": "伊丽丝",
        "string": "……",
        "special": "dia2"
    },
    {
        "name": "伊丽丝",
        "face": "伊丽丝",
        "string": "旅程结束了呢",
        "special": "dia2"
    },
    {
        "name": "世清",
        "face": "世清2",
        "string": "是啊",
        "special": "dia1"
    },
    {
        "name": "世清",
        "face": "世清2",
        "string": "一路上发生了好多事情，所幸最后还是有惊无险",
        "special": "dia1"
    },
    {
        "name": "夏修伦",
        "face": "夏修伦",
        "string": "真舍不得啊",
        "special": "dia2"
    },
    {
        "name": "夏修伦",
        "face": "夏修伦",
        "string": "你接下来有什么打算呢",
        "special": "dia2"
    },
    {
        "name": "世清",
        "face": "世清2",
        "string": "不知道，也许会在这里逗留一段时间",
        "special": "dia1"
    },
    {
        "name": "伊丽丝",
        "face": "伊丽丝",
        "string": "……",
        "special": "dia2"
    },
    {
        "name": "伊丽丝",
        "face": "伊丽丝",
        "string": "要不要跟我一起回去呢？",
        "special": "dia2"
    },
    {
        "name": "伊丽丝",
        "face": "伊丽丝",
        "string": "我想好好感谢一下你",
        "special": "dia2"
    },
    {
        "name": "世清",
        "face": "世清2",
        "string": "这个倒是不用……",
        "special": "dia1"
    },
    {
        "name": "洛雨希",
        "face": "洛雨希",
        "string": "哎呀，你也要学会一下接受别人的好意啊",
        "special": "dia2"
    },
    {
        "name": "洛雨希",
        "face": "洛雨希",
        "string": "夏修伦和我会暂时在这座城市补给一下",
        "special": "dia2"
    },
    {
        "name": "洛雨希",
        "face": "洛雨希",
        "string": "你晚上有空的话，就来酒馆聚一聚吧",
        "special": "dia2"
    },
    {
        "name": "世清",
        "face": "世清2",
        "string": "那好吧……",
        "special": "dia1"
    },
    {
        "name": "洛雨希",
        "face": "洛雨希",
        "string": "再见了，我可爱的伊丽丝，今晚你也要来哦",
        "special": "dia2"
    },
    {
        "name": "夏修伦",
        "face": "夏修伦",
        "string": "对啊，好聚好散",
        "special": "dia2"
    },
    {
        "name": "夏修伦",
        "face": "夏修伦",
        "string": "就先不碍着你们了",
        "special": "dia2"
    },
    {
        "name": "",
        "face": "",
        "string": "夏修伦和洛雨希离队",
        "special": "dia3"
    },
    {
        "name": "伊丽丝",
        "face": "伊丽丝",
        "string": "那我们也走吧",
        "special": "dia2"
    },
    {
        "name": "世清",
        "face": "世清2",
        "string": "嗯",
        "special": "dia1"
    },
    {
        "name": "",
        "face": "",
        "string": "伊拉修莱德宫",
        "special": "dia3"
    },
    {
        "name": "卫兵",
        "face": "",
        "string": "是索菲亚公主！快去禀告陛下！",
        "special": "dia1"
    },
    {
        "name": "世清",
        "face": "世清2",
        "string": "索菲亚？是你的本名吗",
        "special": "dia1"
    },
    {
        "name": "伊丽丝",
        "face": "伊丽丝",
        "string": "是严肃无趣的教名……",
        "special": "dia2"
    },
    {
        "name": "伊丽丝",
        "face": "伊丽丝",
        "string": "有点打击人啊，我还以为会让你感到惊讶呢",
        "special": "dia2"
    },
    {
        "name": "世清",
        "face": "世清2",
        "string": "实际上在之前的旅途中我也猜到九成了",
        "special": "dia1"
    },
    {
        "name": "伊丽丝",
        "face": "伊丽丝",
        "string": "我有一件事想要拜托你",
        "special": "dia2"
    },
    {
        "name": "伊丽丝",
        "face": "伊丽丝",
        "string": "等等如果发生了什么，都像现在这样冷静，好吗？",
        "special": "dia2"
    },
    {
        "name": "世清",
        "face": "世清2",
        "string": "……",
        "special": "dia1"
    },
    {
        "name": "世清",
        "face": "世清2",
        "string": "好",
        "special": "dia1"
    },
    {
        "name": "",
        "face": "",
        "string": "伊拉修莱德宫觐见室",
        "special": "dia3"
    },
    {
        "name": "阿齐兹王",
        "face": "阿齐兹王",
        "string": "终于回来了啊，我的女儿",
        "special": "dia2"
    },
    {
        "name": "伊丽丝",
        "face": "伊丽丝",
        "string": "伊安哥哥呢！？",
        "special": "dia2"
    },
    {
        "name": "阿齐兹王",
        "face": "阿齐兹王",
        "string": "连父亲一句问候都没有，回来就伊安哥哥吗",
        "special": "dia2"
    },
    {
        "name": "阿齐兹王",
        "face": "阿齐兹王",
        "string": "倒也是，如果不是用他的名义，你根本就不可能回来",
        "special": "dia2"
    },
    {
        "name": "伊丽丝",
        "face": "伊丽丝",
        "string": "名义？",
        "special": "dia2"
    },
    {
        "name": "阿齐兹王",
        "face": "阿齐兹王",
        "string": "只有伊安的信鸟回来了",
        "special": "dia2"
    },
    {
        "name": "伊丽丝",
        "face": "伊丽丝",
        "string": "信鸟……？不可能，除非主人出现变故，信鸟不会离开主人",
        "special": "dia2"
    },
    {
        "name": "阿齐兹王",
        "face": "阿齐兹王",
        "string": "就是如此，伊安很可能出现了什么不测，所以这次不能再让你逃婚了",
        "special": "dia2"
    },
    {
        "name": "阿齐兹王",
        "face": "阿齐兹王",
        "string": "你要认识到自己作为伊拉修莱德公主的责任",
        "special": "dia2"
    },
    {
        "name": "伊丽丝",
        "face": "伊丽丝",
        "string": "……为什么可以把事情说得那么轻描淡写啊！",
        "special": "dia2"
    },
    {
        "name": "阿齐兹王",
        "face": "阿齐兹王",
        "string": "……",
        "special": "dia2"
    },
    {
        "name": "阿齐兹王",
        "face": "阿齐兹王",
        "string": "我一直就很奇怪了，这个从一开始就站在你旁边的年轻人是谁？",
        "special": "dia2"
    },
    {
        "name": "伊丽丝",
        "face": "伊丽丝",
        "string": "他……他……",
        "special": "dia2"
    },
    {
        "name": "伊丽丝",
        "face": "伊丽丝",
        "string": "已经和我缔结了誓约的所爱之人",
        "special": "dia2"
    },
    {
        "name": "伊丽丝",
        "face": "伊丽丝",
        "string": "我和他手里的戒指就是证明",
        "special": "dia2"
    },
    {
        "name": "世清",
        "face": "世清2",
        "string": "(……)",
        "special": "dia1"
    },
    {
        "name": "世清",
        "face": "世清2",
        "string": "(原来如此，所以才叫我保持冷静)",
        "special": "dia1"
    },
    {
        "name": "阿齐兹王",
        "face": "阿齐兹王",
        "string": "……",
        "special": "dia2"
    },
    {
        "name": "阿齐兹王",
        "face": "阿齐兹王",
        "string": "真是混账",
        "special": "dia2"
    },
    {
        "name": "阿齐兹王",
        "face": "阿齐兹王",
        "string": "索菲亚，我没有和这个年轻人相处过，所以不知道他有什么优点可以让你痴迷于他",
        "special": "dia2"
    },
    {
        "name": "阿齐兹王",
        "face": "阿齐兹王",
        "string": "但是你要记得你是伊拉修莱德的公主，你的使命是维系王族的关系，让伊拉修莱德继续繁荣下去",
        "special": "dia2"
    },
    {
        "name": "阿齐兹王",
        "face": "阿齐兹王",
        "string": "而不是和没有身份地位的流浪汉结婚",
        "special": "dia2"
    },
    {
        "name": "阿齐兹王",
        "face": "阿齐兹王",
        "string": "卫兵！把这个年轻人送到贵宾囚禁房关押，皇家侍卫给我看好公主",
        "special": "dia2"
    },
    {
        "name": "阿齐兹王",
        "face": "阿齐兹王",
        "string": "年轻人，在索菲亚的联姻完结之前，你给我好好呆着吧，然后拿上你的补偿永远离开这个大陆",
        "special": "dia2"
    },
    {
        "name": "世清",
        "face": "世清2",
        "string": "……",
        "special": "dia1"
    },
    {
        "name": "",
        "face": "",
        "string": "伊拉修莱德宫贵宾囚禁房",
        "special": "dia3"
    },
    {
        "name": "世清",
        "face": "世清2",
        "string": "(于是就这样莫名其妙地坐大牢了)",
        "special": "dia1"
    },
    {
        "name": "世清",
        "face": "世清2",
        "string": "(她是打算利用我作为脱身工具吗？)",
        "special": "dia1"
    },
    {
        "name": "世清",
        "face": "世清2",
        "string": "(不过现在她和我一样也被关起来了吧，光是从结果来说毫无意义)",
        "special": "dia1"
    },
    {
        "name": "世清",
        "face": "世清2",
        "string": "(等等，这个戒指……)",
        "special": "dia1"
    },
    {
        "name": "",
        "face": "",
        "string": "使用信物戒指感知到了密道",
        "special": "dia3"
    },
    {
        "name": "世清",
        "face": "世清2",
        "string": "(原来如此，如果没有这戒指，我不会因为女婿的身份丢到这里，也无法触发这里的机关)",
        "special": "dia1"
    },
    {
        "name": "世清",
        "face": "世清2",
        "string": "(这个城堡和她一样深不可测)",
        "special": "dia1"
    },
    {
        "name": "世清",
        "face": "世清2",
        "string": "(动作得快，被守卫发现逃跑了就麻烦了)",
        "special": "dia1"
    },
    {
        "name": "",
        "face": "",
        "string": "离开监狱，沿着机关密道来到高塔顶层的伊丽丝关押室的窗户外",
        "special": "dia3"
    },
    {
        "name": "世清",
        "face": "世清2",
        "string": "我逃出来了",
        "special": "dia1"
    },
    {
        "name": "伊丽丝",
        "face": "伊丽丝",
        "string": "世清！",
        "special": "dia2"
    },
    {
        "name": "世清",
        "face": "世清2",
        "string": "真是精妙的机关，可以以最隐蔽的角度来到这个吓人的房间",
        "special": "dia1"
    },
    {
        "name": "伊丽丝",
        "face": "伊丽丝",
        "string": "接下来，和我一起发动魔力",
        "special": "dia2"
    },
    {
        "name": "",
        "face": "",
        "string": "激活水路机关，一条肉眼难以看到的冰之路出现在天空中",
        "special": "dia3"
    },
    {
        "name": "伊丽丝",
        "face": "伊丽丝",
        "string": "为了骗过老爸的魔力感知，这个机关一定要两个人配合才会激活",
        "special": "dia2"
    },
    {
        "name": "伊丽丝",
        "face": "伊丽丝",
        "string": "之前哥哥就用这个方法让我逃出去的",
        "special": "dia2"
    },
    {
        "name": "世清",
        "face": "世清2",
        "string": "教会我冰魔法也是计划的一部分么？",
        "special": "dia1"
    },
    {
        "name": "伊丽丝",
        "face": "伊丽丝",
        "string": "……对不起",
        "special": "dia2"
    },
    {
        "name": "世清",
        "face": "世清2",
        "string": "先逃出去再说",
        "special": "dia1"
    },
    {
        "name": "",
        "face": "",
        "string": "顺着架桥逃出了伊拉修莱德宫",
        "special": "dia3"
    },
    {
        "name": "世清",
        "face": "世清2",
        "string": "逃出来了……",
        "special": "dia1"
    },
    {
        "name": "伊丽丝",
        "face": "伊丽丝",
        "string": "……",
        "special": "dia2"
    },
    {
        "name": "伊丽丝",
        "face": "伊丽丝",
        "string": "我很虚伪，是吧",
        "special": "dia2"
    },
    {
        "name": "世清",
        "face": "世清2",
        "string": "……",
        "special": "dia1"
    },
    {
        "name": "世清",
        "face": "世清2",
        "string": "下次说清楚一点，我可以帮是一定会帮的",
        "special": "dia1"
    },
    {
        "name": "伊丽丝",
        "face": "伊丽丝",
        "string": "谢谢……",
        "special": "dia2"
    },
    {
        "name": "伊丽丝",
        "face": "伊丽丝",
        "string": "我讨厌我的爸爸",
        "special": "dia2"
    },
    {
        "name": "伊丽丝",
        "face": "伊丽丝",
        "string": "为了达成目的，可以不择手段利用所有可以利用的东西",
        "special": "dia2"
    },
    {
        "name": "伊丽丝",
        "face": "伊丽丝",
        "string": "可恨的是我同时也继承了他的性格",
        "special": "dia2"
    },
    {
        "name": "世清",
        "face": "世清2",
        "string": "我可以理解",
        "special": "dia1"
    },
    {
        "name": "世清",
        "face": "世清2",
        "string": "只是看起来打算在这里呆几天的计划泡汤了",
        "special": "dia1"
    },
    {
        "name": "伊丽丝",
        "face": "伊丽丝",
        "string": "抱歉……实在是非常对不起",
        "special": "dia2"
    },
    {
        "name": "世清",
        "face": "世清2",
        "string": "不要太自责，其实……",
        "special": "dia1"
    },
    {
        "name": "世清",
        "face": "世清2",
        "string": "虽然只是演戏，但是你搂着我说那句话的时候……还是挺让人……兴奋的",
        "special": "dia1"
    },
    {
        "name": "世清",
        "face": "世清2",
        "string": "就当成是报酬好了",
        "special": "dia1"
    },
    {
        "name": "伊丽丝",
        "face": "伊丽丝",
        "string": "你……你有这么不正经的吗？",
        "special": "dia2"
    },
    {
        "name": "伊丽丝",
        "face": "伊丽丝",
        "string": "不过感觉你这个人真实了很多呢，之前完全猜不透你的性格是什么",
        "special": "dia2"
    },
    {
        "name": "世清",
        "face": "世清2",
        "string": "彼此坦诚相见会让羁绊更深",
        "special": "dia1"
    },
    {
        "name": "世清",
        "face": "世清2",
        "string": "下次要更坦诚一点了，差点我就要那阴暗的房间蹲个几个月了",
        "special": "dia1"
    },
    {
        "name": "伊丽丝",
        "face": "伊丽丝",
        "string": "嘻嘻，我保证没有下次啦",
        "special": "dia2"
    },
    {
        "name": "伊丽丝",
        "face": "伊丽丝",
        "string": "接下来我要去找我那生死不明的哥哥，你没有目标的话，能和我一起走吗？",
        "special": "dia2"
    },
    {
        "name": "世清",
        "face": "世清2",
        "string": "嗯，你能开口，我就会跟着你",
        "special": "dia1"
    },
    {
        "name": "世清",
        "face": "世清2",
        "string": "要去找夏修伦他们吗？虽然继续呆在这里很危险，但是约好和他们在酒馆见面",
        "special": "dia1"
    },
    {
        "name": "世清",
        "face": "世清2",
        "string": "至少和他们说一声吧，就这样走掉感觉过意不去",
        "special": "dia1"
    },
    {
        "name": "伊丽丝",
        "face": "伊丽丝",
        "string": "嗯，我们走吧",
        "special": "dia2"
    }
]