[
    {
        "name": "",
        "face": "",
        "string": "铃兰草原",
        "special": "dia3"
    },
    {
        "name": "宫黄",
        "face": "宫黄",
        "string": "嘿……嘿嘿嘿……嘿嘿嘿嘿",
        "special": "dia2"
    },
    {
        "name": "世清",
        "face": "世清",
        "string": "是你？宫黄",
        "special": "dia1"
    },
    {
        "name": "世清",
        "face": "世清",
        "string": "为什么要救我",
        "special": "dia1"
    },
    {
        "name": "宫黄",
        "face": "宫黄",
        "string": "难道……你所说的……道德……不允许我……救你吗？",
        "special": "dia2"
    },
    {
        "name": "宫黄",
        "face": "宫黄",
        "string": "哈……哈哈……好痛啊……",
        "special": "dia2"
    },
    {
        "name": "宫黄",
        "face": "宫黄",
        "string": "我要死……了吧",
        "special": "dia2"
    },
    {
        "name": "世清",
        "face": "世清",
        "string": "被那个攻击打中……不可能活下来了",
        "special": "dia1"
    },
    {
        "name": "世清",
        "face": "世清",
        "string": "你……为什么",
        "special": "dia1"
    },
    {
        "name": "宫黄",
        "face": "宫黄",
        "string": "别……自作多情……",
        "special": "dia2"
    },
    {
        "name": "宫黄",
        "face": "宫黄",
        "string": "我只是……觉得这样……能感觉到自己……还在这世界上……",
        "special": "dia2"
    },
    {
        "name": "宫黄",
        "face": "宫黄",
        "string": "虽然……短暂……但是……和和歌山一起的日子……很快乐……",
        "special": "dia2"
    },
    {
        "name": "宫黄",
        "face": "宫黄",
        "string": "在和歌山……死后……我感受到了……你所说的……悲哀……",
        "special": "dia2"
    },
    {
        "name": "宫黄",
        "face": "宫黄",
        "string": "孤独……愧疚……后悔……无助……",
        "special": "dia2"
    },
    {
        "name": "宫黄",
        "face": "宫黄",
        "string": "我失去了……一切……在这里到处流浪",
        "special": "dia2"
    },
    {
        "name": "宫黄",
        "face": "宫黄",
        "string": "战争……爆发了……我也……只是……出自本能地……杀戮……徘徊……",
        "special": "dia2"
    },
    {
        "name": "宫黄",
        "face": "宫黄",
        "string": "当我回过神来……就已经在这里了……",
        "special": "dia2"
    },
    {
        "name": "世清",
        "face": "世清",
        "string": "是心中仅存的善念驱使了你本能地救了我一命吗？",
        "special": "dia1"
    },
    {
        "name": "宫黄",
        "face": "宫黄",
        "string": "你爱……这样理解……随你便……",
        "special": "dia2"
    },
    {
        "name": "宫黄",
        "face": "宫黄",
        "string": "……你是一个……令人愤恨的家伙……",
        "special": "dia2"
    },
    {
        "name": "宫黄",
        "face": "宫黄",
        "string": "自幼……就被爱着……有伙伴……伴随你战胜……命运",
        "special": "dia2"
    },
    {
        "name": "宫黄",
        "face": "宫黄",
        "string": "我从……有意识那时起……就被……灌输着……仇恨……",
        "special": "dia2"
    },
    {
        "name": "宫黄",
        "face": "宫黄",
        "string": "我短暂的……人生……被设定为……杀戮……和憎恨……一切……",
        "special": "dia2"
    },
    {
        "name": "宫黄",
        "face": "宫黄",
        "string": "这种感觉……真是……让人……憎恨",
        "special": "dia2"
    },
    {
        "name": "宫黄",
        "face": "宫黄",
        "string": "我也想……和每个……被祝福的生命……一样……度过……一生",
        "special": "dia2"
    },
    {
        "name": "宫黄",
        "face": "宫黄",
        "string": "在这份……愿望下……诞生出了……对自身……更巨大的……憎恨",
        "special": "dia2"
    },
    {
        "name": "宫黄",
        "face": "宫黄",
        "string": "在遇到她之前……我就是憎恨的……化身……憎恨着……这世上的……一切",
        "special": "dia2"
    },
    {
        "name": "宫黄",
        "face": "宫黄",
        "string": "等到……我学会……爱这个世界的……时候……她就离开……我",
        "special": "dia2"
    },
    {
        "name": "宫黄",
        "face": "宫黄",
        "string": "真……羡慕……你啊……",
        "special": "dia2"
    },
    {
        "name": "世清",
        "face": "世清",
        "string": "你这家伙……",
        "special": "dia1"
    },
    {
        "name": "宫黄",
        "face": "宫黄",
        "string": "你被……设定为……我本能地……憎恨的……母体",
        "special": "dia2"
    },
    {
        "name": "宫黄",
        "face": "宫黄",
        "string": "我的内心……被迫接受……取代你的驱动……",
        "special": "dia2"
    },
    {
        "name": "宫黄",
        "face": "宫黄",
        "string": "但是……我一直……不相信……我只是你的……替代品……",
        "special": "dia2"
    },
    {
        "name": "宫黄",
        "face": "宫黄",
        "string": "我不是……你的复制人……我叫……宫黄……我拥有……高贵的……灵魂",
        "special": "dia2"
    },
    {
        "name": "宫黄",
        "face": "宫黄",
        "string": "我会……作为宫黄……这个人……死去",
        "special": "dia2"
    },
    {
        "name": "宫黄",
        "face": "宫黄",
        "string": "我……不奢求……轮回转生……得到自己的幸福……",
        "special": "dia2"
    },
    {
        "name": "宫黄",
        "face": "宫黄",
        "string": "但是……我会作为……宫黄……骄傲地……面对死亡……和轮回……",
        "special": "dia2"
    },
    {
        "name": "宫黄",
        "face": "宫黄",
        "string": "哼……在你身上……浪费了……太多时间了……",
        "special": "dia2"
    },
    {
        "name": "宫黄",
        "face": "宫黄",
        "string": "没来得及……好好看过……这个世界呢……",
        "special": "dia2"
    },
    {
        "name": "宫黄",
        "face": "宫黄",
        "string": "天空……原来是这么蓝的啊……",
        "special": "dia2"
    },
    {
        "name": "",
        "face": "",
        "string": "宫黄断气了",
        "special": "dia3"
    },
    {
        "name": "世清",
        "face": "世清",
        "string": "……",
        "special": "dia1"
    },
    {
        "name": "世清",
        "face": "世清",
        "string": "安息吧……悲哀的生命",
        "special": "dia1"
    },
    {
        "name": "",
        "face": "",
        "string": "安葬好宫黄之后",
        "special": "dia3"
    },
    {
        "name": "世清",
        "face": "世清",
        "string": "四周都变成了战场，余到底去哪了，不会有事吧……",
        "special": "dia1"
    },
    {
        "name": "世清",
        "face": "世清",
        "string": "无论变得多危险，我都要把她找出来",
        "special": "dia1"
    },
    {
        "name": "世清",
        "face": "世清",
        "string": "然后结束这一切……",
        "special": "dia1"
    }
]